{
  "meta": {
    "schemaVersion": "1.0",
    "generatedAt": "2026-07-05T20:20:12.534Z",
    "sourceVersions": {
      "gdelt": "2026-07-05T20:13:31.482Z",
      "acled": "2026-06-26T00:00:00.000Z",
      "ucdp": "2026-07-02T07:41:33.230Z",
      "eia": "2026-07-05T14:12:54.095Z",
      "worldbank": "2026-07-05T14:12:57.009Z"
    },
    "recordCount": 1,
    "breaking": false,
    "staleSourcesPresent": true
  },
  "data": [
    {
      "id": "bfaa5ffed257423a1395",
      "source": "gdelt",
      "type": "conflict",
      "title": "Iran war day 114 : US , Iranian delegations in Switzerland for key talks | US - Israel war on Iran News",
      "description": "",
      "country": "IRN",
      "lat": null,
      "lng": null,
      "severity": 5,
      "date": "2026-06-21",
      "fetchedAt": "2026-06-21T14:00:19.391Z",
      "rawHash": "6498c7143cc03c9d"
    }
  ]
}